tabsdata_bigquery-1.5.0.data/purelib/tabsdata_bigquery/__init__.py
tabsdata_bigquery-1.5.0.data/purelib/tabsdata_bigquery/_connector.py
tabsdata_bigquery-1.5.0.data/purelib/tabsdata_bigquery/assets/manifest/BANNER
tabsdata_bigquery-1.5.0.data/purelib/tabsdata_bigquery/assets/manifest/LICENSE
tabsdata_bigquery-1.5.0.data/purelib/tabsdata_bigquery/assets/manifest/README-PyPi.md
tabsdata_bigquery-1.5.0.data/purelib/tabsdata_bigquery/assets/manifest/RELEASE-NOTES
tabsdata_bigquery-1.5.0.data/purelib/tabsdata_bigquery/assets/manifest/SOURCETRACK.yaml
tabsdata_bigquery-1.5.0.data/purelib/tabsdata_bigquery/assets/manifest/THIRD-PARTY
tabsdata_bigquery-1.5.0.data/purelib/tabsdata_bigquery/assets/manifest/VERSION
tabsdata_bigquery-1.5.0.dist-info/licenses/tabsdata_bigquery/assets/manifest/LICENSE
tabsdata_bigquery-1.5.0.dist-info/METADATA
tabsdata_bigquery-1.5.0.dist-info/WHEEL
tabsdata_bigquery-1.5.0.dist-info/top_level.txt
tabsdata_bigquery-1.5.0.dist-info/RECORD
